{
    "name": "",
    "description": "",
    "addon_category": [
        "User",
        "3D View",
        "Add Curve",
        "Add Mesh",
        "Animation",
        "Baking",
        "Camera",
        "Development",
        "Import-Export",
        "Interface",
        "Lighting",
        "Material",
        "Mesh",
        "Node",
        "Object",
        "Paint",
        "Render",
        "Rigging",
        "Sequencer",
        "System",
        "UV",
        "Video Tools"
    ],
    "repository_name": "",
    "addon_module": "",
    "author": ""
}